WGEasyAPI/__init__.py
WGEasyAPI/connector.py
WGEasyApi/__init__.py
WGEasyApi/connector.py
api_wg_simple-0.10.dist-info/METADATA
api_wg_simple-0.10.dist-info/WHEEL
api_wg_simple-0.10.dist-info/top_level.txt
api_wg_simple-0.10.dist-info/RECORD
